{
  "ingredientItems": [
    {
      "name": "Картофель",
      "type": 0,
      "score": 10,
      "id": "product_potato"
    },
    {
      "name": "Морковь",
      "type": 2,
      "score": 20,
      "id": "product_carrot"
    },
    {
      "name": "Перец",
      "type": 1,
      "score": 30,
      "id": "product_pepper"
    },
    {
      "name": "Лук",
      "type": 3,
      "score": 40,
      "id": "product_onion"
    },
    {
      "name": "Мясо",
      "type": 4,
      "score": 50,
      "id": "product_meat"
    }
  ]
}